xdk/__init__.py
xdk/client.py
xdk/oauth1_auth.py
xdk/oauth2_auth.py
xdk/paginator.py
xdk/streaming.py
xdk/account_activity/__init__.py
xdk/account_activity/client.py
xdk/account_activity/models.py
xdk/activity/__init__.py
xdk/activity/client.py
xdk/activity/models.py
xdk/communities/__init__.py
xdk/communities/client.py
xdk/communities/models.py
xdk/community_notes/__init__.py
xdk/community_notes/client.py
xdk/community_notes/models.py
xdk/compliance/__init__.py
xdk/compliance/client.py
xdk/compliance/models.py
xdk/connections/__init__.py
xdk/connections/client.py
xdk/connections/models.py
xdk/direct_messages/__init__.py
xdk/direct_messages/client.py
xdk/direct_messages/models.py
xdk/general/__init__.py
xdk/general/client.py
xdk/general/models.py
xdk/lists/__init__.py
xdk/lists/client.py
xdk/lists/models.py
xdk/media/__init__.py
xdk/media/client.py
xdk/media/models.py
xdk/news/__init__.py
xdk/news/client.py
xdk/news/models.py
xdk/posts/__init__.py
xdk/posts/client.py
xdk/posts/models.py
xdk/spaces/__init__.py
xdk/spaces/client.py
xdk/spaces/models.py
xdk/stream/__init__.py
xdk/stream/client.py
xdk/stream/models.py
xdk/trends/__init__.py
xdk/trends/client.py
xdk/trends/models.py
xdk/usage/__init__.py
xdk/usage/client.py
xdk/usage/models.py
xdk/users/__init__.py
xdk/users/client.py
xdk/users/models.py
xdk/webhooks/__init__.py
xdk/webhooks/client.py
xdk/webhooks/models.py
xdk-0.5.0.dist-info/METADATA
xdk-0.5.0.dist-info/WHEEL
xdk-0.5.0.dist-info/RECORD
