Metadata-Version: 2.4
Name: xdk
Version: 0.5.0
Summary: Python SDK for the X API
Project-URL: Homepage, https://github.com/xdevplatform/xdk-python
Project-URL: Repository, https://github.com/xdevplatform/xdk-python
Author-email: X Developer Platform <devs@x.com>
Classifier: Development Status :: 3 - Alpha
Classifier: Intended Audience :: Developers
Classifier: License :: OSI Approved :: MIT License
Classifier: Programming Language :: Python :: 3
Classifier: Programming Language :: Python :: 3.8
Classifier: Programming Language :: Python :: 3.9
Classifier: Programming Language :: Python :: 3.10
Classifier: Programming Language :: Python :: 3.11
Classifier: Programming Language :: Python :: 3.12
Requires-Python: >=3.8
Requires-Dist: pydantic>=2.0.0
Requires-Dist: requests-oauthlib>=1.3.0
Requires-Dist: requests>=2.25.0
Provides-Extra: dev
Requires-Dist: black; extra == 'dev'
Requires-Dist: myst-parser>=2.0.0; extra == 'dev'
Requires-Dist: pytest; extra == 'dev'
Requires-Dist: pytest-cov; extra == 'dev'
Requires-Dist: ruff; extra == 'dev'
Requires-Dist: sphinx-markdown-builder>=0.5.5; extra == 'dev'
Requires-Dist: sphinx>=7.0.0; extra == 'dev'
Requires-Dist: watchdog>=3.0.0; extra == 'dev'
